<odoo>
    <record id="view_order_form_inherit_hpp" model="ir.ui.view">
        <field name="name">purchase.order.form.inherit.hpp</field>
        <field name="model">purchase.order</field>
        <field name="inherit_id" ref="purchase.purchase_order_form"/>
        <field name="arch" type="xml">
            <xpath expr="//field[@name='order_line']/tree/field[@name='price_unit']" position="after">
                <field name="hpp"/>
                <field name="rest_po"/>
                <field name="po_ita"/>
                <field name="rest_po_total"/>
            </xpath>
        </field>
    </record>

    <!-- <record id="view_currency_form_inherit_hpp_factor" model="ir.ui.view">
        <field name="name">res.currency.form.inherit.hpp.factor</field>
        <field name="model">res.currency</field>
        <field name="inherit_id" ref="base.view_currency_form"/>
        <field name="arch" type="xml">
            <xpath expr="//group" position="inside">
                <field name="hpp_factor"/>
            </xpath>
        </field>
    </record> -->
    <record id="view_currency_rate_form_inherit_hpp_factor" model="ir.ui.view">
        <field name="name">res.currency.rate.form.inherit.hpp.factor</field>
        <field name="model">res.currency.rate</field>
        <field name="inherit_id" ref="base.view_currency_rate_form"/>
        <field name="arch" type="xml">
            <xpath expr="//field[@name='rate']" position="before">
                <field name="hpp_factor"/>
            </xpath>
        </field>
    </record>

    <record id="view_currency_rate_tree_inherit_hpp_factor" model="ir.ui.view">
        <field name="name">res.currency.rate.tree.inherit.hpp.factor</field>
        <field name="model">res.currency.rate</field>
        <field name="inherit_id" ref="base.view_currency_rate_tree"/>
        <field name="arch" type="xml">
            <xpath expr="//field[@name='rate']" position="before">
                <field name="hpp_factor"/>
            </xpath>
        </field>
    </record>
</odoo>

<!-- <field name="hpp" attrs="{'column_invisible': [('parent.state', 'not in', ('purchase', 'done'))]}" optional="show"/>
                <field name="rest_po" attrs="{'column_invisible': [('parent.state', 'not in', ('purchase', 'done'))]}" optional="show"/> -->